nlp2fn/__init__.py
nlp2fn/clonefromgit.py
nlp2fn/interface.py
nlp2fn/sourcehandler/__init__.py
nlp2fn/sourcehandler/helper.py
nlp2fn/sourcehandler/sourcemodel.py
nlp2fn/sourcehandler/git/__init__.py
nlp2fn/sourcehandler/git/repo.py
nlp2fn/utils/__init__.py
nlp2fn/utils/colorpriniting.py
nlp2fn/utils/commands.py
nlp2fn/utils/configparser.py
nlp2fn/utils/detectenv.py
nlp2fn/utils/fncloader.py
nlp2fn-0.0.4.dist-info/METADATA
nlp2fn-0.0.4.dist-info/WHEEL
nlp2fn-0.0.4.dist-info/entry_points.txt
nlp2fn-0.0.4.dist-info/top_level.txt
nlp2fn-0.0.4.dist-info/RECORD
