Metadata-Version: 2.1
Name: nlp2fn
Version: 0.0.4
Summary: With the ability to load and read Python functions from any specified location, `nlp2fn` brings all your automation tasks together.
Home-page: https://github.com/dextrop/nlp2fn
Author: Jennie Developers <saurabh@ask-jennie.com>
Author-email: Jennie Developers <saurabh@ask-jennie.com>
Classifier: License :: OSI Approved :: MIT License
Classifier: Programming Language :: Python :: 3
Classifier: Programming Language :: Python :: 3.7
Requires-Dist: requests
